{
  "data": {
    "people": [
      {
        "name": "Oleg Artemyev",
        "craft": "ISS",
        "thumbnailUrl": "https://tse2.mm.bing.net/th?id=OIP.N8N2ltB9ZFJhp2cubBn_OgHaLH&pid=Api",
        "contentUrl": "http://spaceflight101.com/iss/wp-content/uploads/sites/37/2018/02/ArtemyevGCTC.jpg"
      },
      {
        "name": "Denis Matveev",
        "craft": "ISS",
        "thumbnailUrl": "https://tse4.mm.bing.net/th?id=OIP.p-g11UPO13oIbpfhMdCZrQHaLW&pid=Api",
        "contentUrl": "https://spacelaunchnow-prod-east.nyc3.digitaloceanspaces.com/media/astronaut_images/denis_matveev_image_20210504184409.jpg"
      },
      {
        "name": "Sergey Korsakov",
        "craft": "ISS",
        "thumbnailUrl": "https://tse1.mm.bing.net/th?id=OIP.NRePhET4iXsLxq8nSncMiwHaHa&pid=Api",
        "contentUrl": "https://www.researchgate.net/profile/Alla-Vein/publication/323352779/figure/fig2/AS:597012965752832@1519350391689/Sergey-Korsakov-1854-1900_Q640.jpg"
      },
      {
        "name": "Kjell Lindgren",
        "craft": "ISS",
        "thumbnailUrl": "https://tse3.mm.bing.net/th?id=OIP.lOdbBOmuXIgywWr4u7wOkgHaLH&pid=Api",
        "contentUrl": "http://www.nasa.gov/sites/default/files/thumbnails/image/jsc2015e053682.jpg"
      },
      {
        "name": "Bob Hines",
        "craft": "ISS",
        "thumbnailUrl": "https://tse2.mm.bing.net/th?id=OIP.AS7PYu58C1dHtcIltrI8RQHaEK&pid=Api",
        "contentUrl": "https://i.ytimg.com/vi/DPhPX33Dlr0/maxresdefault.jpg"
      },
      {
        "name": "Samantha Cristoforetti",
        "craft": "ISS",
        "thumbnailUrl": "https://tse2.mm.bing.net/th?id=OIP.C7-Bvqjzve1oY10lYVw8kwHaGX&pid=Api",
        "contentUrl": "https://blogs.esa.int/exploration/files/2019/12/Samantha_Cristoforetti_official_portrait-e1583312822755.jpg"
      },
      {
        "name": "Jessica Watkins",
        "craft": "ISS",
        "thumbnailUrl": "https://tse1.mm.bing.net/th?id=OIP.ZHd6fKvhp_QGokaRc7LnlQHaJQ&pid=Api",
        "contentUrl": "https://imgix.elitedaily.com/uploads/image/2020/1/29/32dc54dc-c26b-4662-847a-ba7098251da4-44763373721_d83d3b6d7f_k.jpg"
      },
      {
        "name": "Cai Xuzhe",
        "craft": "Tiangong",
        "thumbnailUrl": "https://tse1.mm.bing.net/th?id=OIP.0B6TbIVo7ThGi4jUFR8wWgHaEK&pid=Api",
        "contentUrl": "https://video.cgtn.com/news/2022-09-17/Space-Log-Taikonaut-Cai-Xuzhe-leaves-cabin-for-EVAs-1doYfKLM46c/video/6a3e5891031a4e6f90fc3ad1b8bc95e2/6a3e5891031a4e6f90fc3ad1b8bc95e2-1280.jpg"
      },
      {
        "name": "Chen Dong",
        "craft": "Tiangong",
        "thumbnailUrl": "https://tse2.mm.bing.net/th?id=OIP.oLzSkCb3Tzgf2OYP1SNw9gHaHa&pid=Api",
        "contentUrl": "https://i1.rgstatic.net/ii/profile.image/642695164882945-1530241876050_Q512/Chen-Dong-19.jpg"
      },
      {
        "name": "Liu Yang",
        "craft": "Tiangong",
        "thumbnailUrl": "https://tse1.mm.bing.net/th?id=OIP.ETH7-P_WHlkcXoi8i6xqrgHaIX&pid=Api",
        "contentUrl": "http://img.maxisciences.com/article/1024/international/la-chinoise-liu-yang-agee-de-34-ans-est-pilote-de-chasse_a75973d98ad8117031b33b80a305c3ad35cef5bf.jpg"
      },
      {
        "name": "Sergey Prokopyev",
        "craft": "ISS",
        "thumbnailUrl": "https://tse1.mm.bing.net/th?id=OIP.CfrxNv3BUzzjGRyTIAsrzAHaLH&pid=Api",
        "contentUrl": "https://www.spacelaunchschedule.com/wp-content/uploads/sergey2520prokopyev_image_20181207031221.jpeg"
      },
      {
        "name": "Dmitry Petelin",
        "craft": "ISS",
        "thumbnailUrl": "https://tse3.mm.bing.net/th?id=OIP.80ArFBvWGZGcq1u8-ch1ZQHaHa&pid=Api",
        "contentUrl": "https://i1.rgstatic.net/ii/profile.image/324459217522688-1454368513160_Q512/Dmitry_Petelin.jpg"
      },
      {
        "name": "Frank Rubio",
        "craft": "ISS",
        "thumbnailUrl": "https://tse3.mm.bing.net/th?id=OIP.vS_lm6RdpP-YgR1SqWB7fQHaJQ&pid=Api",
        "contentUrl": "http://www.nasa.gov/sites/default/files/thumbnails/image/jsc2017e114795.jpg"
      }
    ],
    "number": 13,
    "message": "success"
  }
}