{
  "data": {
    "people": [
      {
        "name": "Raja Chari",
        "craft": "ISS",
        "thumbnailUrl": "https://tse4.mm.bing.net/th?id=OIP.06DslEAi2pYJi2nMCZ-sBQHaFw&pid=Api",
        "contentUrl": "https://www.americanbazaaronline.com/wp-content/uploads/2020/12/Raja-Chari.jpg"
      },
      {
        "name": "Tom Marshburn",
        "craft": "ISS",
        "thumbnailUrl": "https://tse3.mm.bing.net/th?id=OIP.DRrF2-SFrrINBFWp21Jg5gHaJQ&pid=Api",
        "contentUrl": "http://www.nasa.gov/images/content/58869main_ascan_marshburn_8x10.jpg"
      },
      {
        "name": "Kayla Barron",
        "craft": "ISS",
        "thumbnailUrl": "https://tse1.mm.bing.net/th?id=OIP.bkAmHdk5oWdFc4ukYb-WjwHaJQ&pid=Api",
        "contentUrl": "https://scitechdaily.com/images/NASA-Astronaut-Kayla-Barron-1229x1536.jpg"
      },
      {
        "name": "Matthias Maurer",
        "craft": "ISS",
        "thumbnailUrl": "https://tse1.mm.bing.net/th?id=OIP.gi8dogeEx2UQRbU2ii8YUwHaJe&pid=Api",
        "contentUrl": "https://www.cl24.cl/u/fotografias/fotosnoticias/2020/12/15/9038.jpg"
      },
      {
        "name": "Oleg Artemyev",
        "craft": "ISS",
        "thumbnailUrl": "https://tse3.mm.bing.net/th?id=OIP.cSWv_rSR09WNy8kISCU_EAHaLG&pid=Api",
        "contentUrl": "http://www.spacefacts.de/bios/portraits_hi/cosmonauts/artemyev_oleg.jpg"
      },
      {
        "name": "Denis Matveev",
        "craft": "ISS",
        "thumbnailUrl": "https://tse3.mm.bing.net/th?id=OIP.BNNOGmsy5plj82sW8Oe3bAHaLW&pid=Api",
        "contentUrl": "https://www.spacelaunchschedule.com/wp-content/uploads/denis_matveev_image_20210504184409-668x1024.jpg"
      },
      {
        "name": "Sergey Korsakov",
        "craft": "ISS",
        "thumbnailUrl": "https://tse1.mm.bing.net/th?id=OIP.NRePhET4iXsLxq8nSncMiwHaHa&pid=Api",
        "contentUrl": "https://www.researchgate.net/profile/Alla-Vein/publication/323352779/figure/fig2/AS:597012965752832@1519350391689/Sergey-Korsakov-1854-1900_Q640.jpg"
      }
    ],
    "number": 7,
    "message": "success"
  }
}